simple_http_validator/__init__.py
simple_http_validator/checker.py
simple_http_validator/cli.py
simple_http_validator-1.2.1.dist-info/METADATA
simple_http_validator-1.2.1.dist-info/WHEEL
simple_http_validator-1.2.1.dist-info/entry_points.txt
simple_http_validator-1.2.1.dist-info/top_level.txt
simple_http_validator-1.2.1.dist-info/RECORD
